vesin/torch/__init__.py
vesin/torch/_c_lib.py
vesin/torch/_neighbors.py
vesin/torch/torch-2.3/include/vesin_torch.hpp
vesin/torch/torch-2.3/lib/libvesin_torch.dylib
vesin/torch/torch-2.4/include/vesin_torch.hpp
vesin/torch/torch-2.4/lib/libvesin_torch.dylib
vesin/torch/torch-2.5/include/vesin_torch.hpp
vesin/torch/torch-2.5/lib/libvesin_torch.dylib
vesin/torch/torch-2.6/include/vesin_torch.hpp
vesin/torch/torch-2.6/lib/libvesin_torch.dylib
vesin/torch/torch-2.7/include/vesin_torch.hpp
vesin/torch/torch-2.7/lib/libvesin_torch.dylib
vesin/torch/torch-2.8/include/vesin_torch.hpp
vesin/torch/torch-2.8/lib/libvesin_torch.dylib
vesin/torch/torch-2.9/include/vesin_torch.hpp
vesin/torch/torch-2.9/lib/libvesin_torch.dylib
vesin_torch-0.4.2.dist-info/METADATA
vesin_torch-0.4.2.dist-info/WHEEL
vesin_torch-0.4.2.dist-info/top_level.txt
vesin_torch-0.4.2.dist-info/RECORD
