Metadata-Version: 2.4
Name: vesin-torch
Version: 0.4.2
Summary: Computing neighbor lists for atomistic system, in TorchScript
Author-email: Guillaume Fraux <guillaume.fraux@epfl.ch>
License-Expression: BSD-3-Clause
Project-URL: homepage, https://github.com/Luthaf/vesin/
Project-URL: documentation, https://luthaf.fr/vesin/
Project-URL: repository, https://github.com/Luthaf/vesin/
Project-URL: changelog, https://github.com/Luthaf/vesin/blob/main/CHANEGELOG.md
Classifier: Development Status :: 4 - Beta
Classifier: Intended Audience :: Science/Research
Classifier: Operating System :: POSIX
Classifier: Operating System :: MacOS :: MacOS X
Classifier: Operating System :: Microsoft :: Windows
Classifier: Programming Language :: Python
Classifier: Programming Language :: Python :: 3
Classifier: Topic :: Scientific/Engineering
Classifier: Topic :: Scientific/Engineering :: Bio-Informatics
Classifier: Topic :: Scientific/Engineering :: Chemistry
Classifier: Topic :: Scientific/Engineering :: Physics
Classifier: Topic :: Software Development :: Libraries
Classifier: Topic :: Software Development :: Libraries :: Python Modules
Requires-Python: >=3.10
Requires-Dist: torch >=2.3,<2.10
Dynamic: requires-dist
